instafill/__init__.py
instafill/client.py
instafill-0.0.7.dist-info/LICENSE
instafill-0.0.7.dist-info/METADATA
instafill-0.0.7.dist-info/WHEEL
instafill-0.0.7.dist-info/top_level.txt
instafill-0.0.7.dist-info/RECORD
