Metadata-Version: 2.2
Name: instafill
Version: 0.0.7
Summary: A tool to automatically fill PDF forms
Author-email: instafill-ai <api@instafill.ai>
Project-URL: Homepage, https://instafill.ai
Classifier: Programming Language :: Python :: 3
Classifier: License :: OSI Approved :: MIT License
Classifier: Operating System :: OS Independent
Requires-Python: >=3.8
License-File: LICENSE
